wagtail_dynamic_choice/__init__.py
wagtail_dynamic_choice/apps.py
wagtail_dynamic_choice/blocks.py
wagtail_dynamic_choice/form_fields.py
wagtail_dynamic_choice/function_specifier.py
wagtail_dynamic_choice/model_fields.py
wagtail_dynamic_choice/widgets.py
wagtail_dynamic_choice-4.1.0.dist-info/AUTHORS.txt
wagtail_dynamic_choice-4.1.0.dist-info/LICENSE.txt
wagtail_dynamic_choice-4.1.0.dist-info/METADATA
wagtail_dynamic_choice-4.1.0.dist-info/WHEEL
wagtail_dynamic_choice-4.1.0.dist-info/top_level.txt
wagtail_dynamic_choice-4.1.0.dist-info/zip-safe
wagtail_dynamic_choice-4.1.0.dist-info/RECORD
